fablinker
